usportspy/__init__.py
usportspy/basketball.py
usportspy/crosscountry.py
usportspy/fieldhockey.py
usportspy/football.py
usportspy/helpers.py
usportspy/icehockey.py
usportspy/rugby.py
usportspy/soccer.py
usportspy/swimming.py
usportspy/trackandfield.py
usportspy/volleyball.py
usportspy/wrestling.py
usportspy-0.0.11.dist-info/METADATA
usportspy-0.0.11.dist-info/WHEEL
usportspy-0.0.11.dist-info/top_level.txt
usportspy-0.0.11.dist-info/RECORD
