Metadata-Version: 2.1
Name: usportspy
Version: 0.0.11
Summary: Extract and Analyze Data from U SPORTS, the Governing Body of University Sport in Canada. 
Requires-Dist: requests
Requires-Dist: pandas
Requires-Dist: pyjanitor
